scrambler/__init__.py
scrambler/command.py
scrambler/tests/__init__.py
scrambler/tests/test_scramble.py
scrambler-0.0.5.dist-info/DESCRIPTION.rst
scrambler-0.0.5.dist-info/entry_points.txt
scrambler-0.0.5.dist-info/METADATA
scrambler-0.0.5.dist-info/metadata.json
scrambler-0.0.5.dist-info/RECORD
scrambler-0.0.5.dist-info/top_level.txt
scrambler-0.0.5.dist-info/WHEEL
