Metadata-Version: 2.0
Name: scrambler
Version: 0.0.5
Summary: Symlink (namespaced) python packages into a single folder to aid development
Home-page: http://github.com/phlax/scrambler
Author: Ryan Northey
Author-email: ryan@3ca.org.uk
License: GPL
Platform: UNKNOWN
Classifier: Development Status :: 4 - Beta
Classifier: Intended Audience :: Developers
Classifier: Programming Language :: Python :: 2
Classifier: Programming Language :: Python :: 2.6
Classifier: Programming Language :: Python :: 2.7
Classifier: Programming Language :: Python :: 3
Classifier: Programming Language :: Python :: 3.2
Classifier: Programming Language :: Python :: 3.3
Classifier: Programming Language :: Python :: 3.4
Classifier: Topic :: Software Development :: Libraries :: Python Modules
Requires-Dist: setuptools
